pyblustream/__init__.py
pyblustream/listener.py
pyblustream/matrix.py
pyblustream/protocol.py
pyblustream-0.21.dist-info/LICENSE.md
pyblustream-0.21.dist-info/METADATA
pyblustream-0.21.dist-info/WHEEL
pyblustream-0.21.dist-info/top_level.txt
pyblustream-0.21.dist-info/RECORD
