Metadata-Version: 2.1
Name: pyblustream
Version: 0.21
Summary: Control Blustream and Elan HDBaseT Matrix
Home-page: https://github.com/designer-living/pyblustream
Download-URL: https://github.com/foxy82/designer-living/archive/0.21.tar.gz
Author: foxy82
Author-email: foxy82.github@gmail.com
License: Apache 2.0
Keywords: Blustream,Elan,HDBaseT
Classifier: Development Status :: 5 - Production/Stable
Classifier: Intended Audience :: Developers
Classifier: Topic :: Software Development :: Build Tools
Classifier: License :: OSI Approved :: Apache Software License
Classifier: Programming Language :: Python :: 3.10
License-File: LICENSE.md
Requires-Dist: aiohttp >=3.8.3
Requires-Dist: xmltodict >=0.11.0
